backup_pro/__init__.py
backup_pro/__main__.py
backup_pro/backup_pro.py
backup_pro/cli.py
backup_pro/constants.py
backup_pro/common/entity.py
backup_pro/common/singleton.py
backup_pro/common/utils.py
backup_pro/repository/__init__.py
backup_pro/repository/dao.py
backup_pro/repository/repository.py
backup_pro/services/__init__.py
backup_pro/services/archive_service.py
backup_pro/services/configuration_service.py
backup_pro/services/dto.py
backup_pro/services/package_service.py
backup_pro/services/scan_service.py
backup_pro-1.0.1.dist-info/METADATA
backup_pro-1.0.1.dist-info/WHEEL
backup_pro-1.0.1.dist-info/licenses/LICENSE
backup_pro-1.0.1.dist-info/RECORD
