Metadata-Version: 2.1
Name: backup-pro
Version: 1.0.1
Summary: A comprehensive backup tool that makes the life easier when backing up/restoring configurations, files, packages of the system.
Project-URL: Homepage, https://github.com/simsekhalit/backup-pro
Author-email: Halit Simsek <mail.simsekhalit@gmail.com>
License: MIT License
License-File: LICENSE
Keywords: apt,archive,backup,backup-pro,cli,configuration,diff,flatpak,gsettings,package,pro,recovery,restore,scan,snap
Classifier: Development Status :: 5 - Production/Stable
Classifier: License :: OSI Approved :: MIT License
Classifier: Operating System :: OS Independent
Classifier: Programming Language :: Python :: 3
Classifier: Programming Language :: Python :: 3.10
Classifier: Programming Language :: Python :: 3.11
Classifier: Programming Language :: Python :: 3.12
Classifier: Programming Language :: Python :: 3.13
Classifier: Programming Language :: Python :: Implementation :: CPython
Classifier: Programming Language :: Python :: Implementation :: PyPy
Classifier: Topic :: System :: Archiving :: Backup
Requires-Python: >=3.10
Requires-Dist: attrs~=23.1
Requires-Dist: cattrs~=23.1
Provides-Extra: ujson
Requires-Dist: ujson~=5.8; implementation_name == 'cpython' and extra == 'ujson'
